ETH_Terminal/__init__.py
ETH_Terminal/utils.py
nonebot2_plugin_eth_terminal-0.0.2.dist-info/WHEEL
nonebot2_plugin_eth_terminal-0.0.2.dist-info/METADATA
nonebot2_plugin_eth_terminal-0.0.2.dist-info/RECORD
